kkapi/__init__.py
kkapi/auth.py
kkapi/callback.py
kkapi/client.py
kkapi/config.py
kkapi/models.py
kkapi/oepoll.py
kkapi/server.py
kkapi/session.py
kkapi/talk.py
kkapi-1.2.dist-info/DESCRIPTION.rst
kkapi-1.2.dist-info/METADATA
kkapi-1.2.dist-info/RECORD
kkapi-1.2.dist-info/WHEEL
kkapi-1.2.dist-info/metadata.json
kkapi-1.2.dist-info/top_level.txt
