Metadata-Version: 2.0
Name: kkapi
Version: 1.2
Summary: 半垢API
Home-page: UNKNOWN
Author: 育柔
Author-email: UNKNOWN
License: MIT 育柔
Platform: UNKNOWN
